cop/__init__.py
cop/cop.py
modipyCop-1.2.1.dist-info/LICENSE
modipyCop-1.2.1.dist-info/METADATA
modipyCop-1.2.1.dist-info/WHEEL
modipyCop-1.2.1.dist-info/top_level.txt
modipyCop-1.2.1.dist-info/RECORD
