Metadata-Version: 2.1
Name: modipyCop
Version: 1.2.1
Summary: Track modification made to file/s.
Home-page: https://github.com/niCodeLine/modipy
Author: Nico Spok
Author-email: nicospok@hotmail.com
License: MIT
Classifier: Programming Language :: Python :: 3
Classifier: License :: OSI Approved :: MIT License
Classifier: Operating System :: OS Independent
Requires-Python: >=3.6
License-File: LICENSE
